Workbook

Sheet Fournisseurs_DB
A1: ID_Facture | B1: Fournisseur / Client | C1: Numéro_Facture | D1: Date_Emission | E1: Montant_HT | F1: Montant_TVA | G1: Montant_TTC | H1: Taux_TVA | I1: Catégorie | J1: Lien_PDF | K1: Statut_Paiement | L1: Date_Import | M1: Source_Extraction | N1: Date_Règlement

Sheet Clients_DB
A1: ID_Facture | B1: Fournisseur / Client | C1: Numéro_Facture | D1: Date_Emission | E1: Montant_HT | F1: Montant_TVA | G1: Montant_TTC | H1: Taux_TVA | I1: Catégorie | J1: Lien_PDF | K1: Statut_Paiement | L1: Date_Import | M1: Source_Extraction | N1: Date_Règlement

Sheet PDF_Import
A1: IMPORTATION DE FACTURE PDF
A3: 1. SÉLECTIONNER LE FICHIER PDF
A5: Fichier PDF : | D5: ← Bouton créé par VBA
A7: 2. DONNÉES EXTRAITES AUTOMATIQUEMENT
A9: Numéro de facture :
A10: Date d'émission :
A11: Montant HT (€) :
A12: Montant TVA (€) :
A13: Montant TTC (€) :
A14: Taux TVA (%) :
A15: Type de facture :
A17: 3. ACTIONS
A18: → Les boutons ci-dessous sont créés automatiquement par la macro VBA Setup_Boutons
A22: STATUT
A23: En attente d'importation...

Sheet Pivot_Analytics
A1: TABLEAU DE BORD ANALYTIQUE
A3: Année affichée : | B3: =TVA_Mensuelle!B3 | C3: (modifiable dans TVA_Mensuelle, cellule B3)
A4: Mois | B4: CA HT (Clients) | C4: Dépenses HT (Fournisseurs) | D4: TVA Collectée | E4: TVA Déductible | F4: Solde TVA
A5: Janvier | B5: =IFERROR(SUMPRODUCT((MONTH(Clients_DB[Date_Emission])=1)*(YEAR(Clients_DB[Date_Emission])=TVA_Mensuelle!$B$3)*Clients_DB[Montant_HT]),0) | C5: =IFERROR(SUMPRODUCT((MONTH(Fournisseurs_DB[Date_Emission])=1)*(YEAR(Fournisseurs_DB[Date_Emission])=TVA_Mensuelle!$B$3)*Fournisseurs_DB[Montant_HT]),0) | D5: =IFERROR(SUMPRODUCT((MONTH(Clients_DB[Date_Emission])=1)*(YEAR(Clients_DB[Date_Emission])=TVA_Mensuelle!$B$3)*Clients_DB[Montant_TVA]),0) | E5: =IFERROR(SUMPRODUCT((MONTH(Fournisseurs_DB[Date_Emission])=1)*(YEAR(Fournisseurs_DB[Date_Emission])=TVA_Mensuelle!$B$3)*Fournisseurs_DB[Montant_TVA]),0) | F5: =D5-E5
A6: Février | B6: =IFERROR(SUMPRODUCT((MONTH(Clients_DB[Date_Emission])=2)*(YEAR(Clients_DB[Date_Emission])=TVA_Mensuelle!$B$3)*Clients_DB[Montant_HT]),0) | C6: =IFERROR(SUMPRODUCT((MONTH(Fournisseurs_DB[Date_Emission])=2)*(YEAR(Fournisseurs_DB[Date_Emission])=TVA_Mensuelle!$B$3)*Fournisseurs_DB[Montant_HT]),0) | D6: =IFERROR(SUMPRODUCT((MONTH(Clients_DB[Date_Emission])=2)*(YEAR(Clients_DB[Date_Emission])=TVA_Mensuelle!$B$3)*Clients_DB[Montant_TVA]),0) | E6: =IFERROR(SUMPRODUCT((MONTH(Fournisseurs_DB[Date_Emission])=2)*(YEAR(Fournisseurs_DB[Date_Emission])=TVA_Mensuelle!$B$3)*Fournisseurs_DB[Montant_TVA]),0) | F6: =D6-E6
A7: Mars | B7: =IFERROR(SUMPRODUCT((MONTH(Clients_DB[Date_Emission])=3)*(YEAR(Clients_DB[Date_Emission])=TVA_Mensuelle!$B$3)*Clients_DB[Montant_HT]),0) | C7: =IFERROR(SUMPRODUCT((MONTH(Fournisseurs_DB[Date_Emission])=3)*(YEAR(Fournisseurs_DB[Date_Emission])=TVA_Mensuelle!$B$3)*Fournisseurs_DB[Montant_HT]),0) | D7: =IFERROR(SUMPRODUCT((MONTH(Clients_DB[Date_Emission])=3)*(YEAR(Clients_DB[Date_Emission])=TVA_Mensuelle!$B$3)*Clients_DB[Montant_TVA]),0) | E7: =IFERROR(SUMPRODUCT((MONTH(Fournisseurs_DB[Date_Emission])=3)*(YEAR(Fournisseurs_DB[Date_Emission])=TVA_Mensuelle!$B$3)*Fournisseurs_DB[Montant_TVA]),0) | F7: =D7-E7
A8: Avril | B8: =IFERROR(SUMPRODUCT((MONTH(Clients_DB[Date_Emission])=4)*(YEAR(Clients_DB[Date_Emission])=TVA_Mensuelle!$B$3)*Clients_DB[Montant_HT]),0) | C8: =IFERROR(SUMPRODUCT((MONTH(Fournisseurs_DB[Date_Emission])=4)*(YEAR(Fournisseurs_DB[Date_Emission])=TVA_Mensuelle!$B$3)*Fournisseurs_DB[Montant_HT]),0) | D8: =IFERROR(SUMPRODUCT((MONTH(Clients_DB[Date_Emission])=4)*(YEAR(Clients_DB[Date_Emission])=TVA_Mensuelle!$B$3)*Clients_DB[Montant_TVA]),0) | E8: =IFERROR(SUMPRODUCT((MONTH(Fournisseurs_DB[Date_Emission])=4)*(YEAR(Fournisseurs_DB[Date_Emission])=TVA_Mensuelle!$B$3)*Fournisseurs_DB[Montant_TVA]),0) | F8: =D8-E8
A9: Mai | B9: =IFERROR(SUMPRODUCT((MONTH(Clients_DB[Date_Emission])=5)*(YEAR(Clients_DB[Date_Emission])=TVA_Mensuelle!$B$3)*Clients_DB[Montant_HT]),0) | C9: =IFERROR(SUMPRODUCT((MONTH(Fournisseurs_DB[Date_Emission])=5)*(YEAR(Fournisseurs_DB[Date_Emission])=TVA_Mensuelle!$B$3)*Fournisseurs_DB[Montant_HT]),0) | D9: =IFERROR(SUMPRODUCT((MONTH(Clients_DB[Date_Emission])=5)*(YEAR(Clients_DB[Date_Emission])=TVA_Mensuelle!$B$3)*Clients_DB[Montant_TVA]),0) | E9: =IFERROR(SUMPRODUCT((MONTH(Fournisseurs_DB[Date_Emission])=5)*(YEAR(Fournisseurs_DB[Date_Emission])=TVA_Mensuelle!$B$3)*Fournisseurs_DB[Montant_TVA]),0) | F9: =D9-E9
A10: Juin | B10: =IFERROR(SUMPRODUCT((MONTH(Clients_DB[Date_Emission])=6)*(YEAR(Clients_DB[Date_Emission])=TVA_Mensuelle!$B$3)*Clients_DB[Montant_HT]),0) | C10: =IFERROR(SUMPRODUCT((MONTH(Fournisseurs_DB[Date_Emission])=6)*(YEAR(Fournisseurs_DB[Date_Emission])=TVA_Mensuelle!$B$3)*Fournisseurs_DB[Montant_HT]),0) | D10: =IFERROR(SUMPRODUCT((MONTH(Clients_DB[Date_Emission])=6)*(YEAR(Clients_DB[Date_Emission])=TVA_Mensuelle!$B$3)*Clients_DB[Montant_TVA]),0) | E10: =IFERROR(SUMPRODUCT((MONTH(Fournisseurs_DB[Date_Emission])=6)*(YEAR(Fournisseurs_DB[Date_Emission])=TVA_Mensuelle!$B$3)*Fournisseurs_DB[Montant_TVA]),0) | F10: =D10-E10
A11: Juillet | B11: =IFERROR(SUMPRODUCT((MONTH(Clients_DB[Date_Emission])=7)*(YEAR(Clients_DB[Date_Emission])=TVA_Mensuelle!$B$3)*Clients_DB[Montant_HT]),0) | C11: =IFERROR(SUMPRODUCT((MONTH(Fournisseurs_DB[Date_Emission])=7)*(YEAR(Fournisseurs_DB[Date_Emission])=TVA_Mensuelle!$B$3)*Fournisseurs_DB[Montant_HT]),0) | D11: =IFERROR(SUMPRODUCT((MONTH(Clients_DB[Date_Emission])=7)*(YEAR(Clients_DB[Date_Emission])=TVA_Mensuelle!$B$3)*Clients_DB[Montant_TVA]),0) | E11: =IFERROR(SUMPRODUCT((MONTH(Fournisseurs_DB[Date_Emission])=7)*(YEAR(Fournisseurs_DB[Date_Emission])=TVA_Mensuelle!$B$3)*Fournisseurs_DB[Montant_TVA]),0) | F11: =D11-E11
A12: Août | B12: =IFERROR(SUMPRODUCT((MONTH(Clients_DB[Date_Emission])=8)*(YEAR(Clients_DB[Date_Emission])=TVA_Mensuelle!$B$3)*Clients_DB[Montant_HT]),0) | C12: =IFERROR(SUMPRODUCT((MONTH(Fournisseurs_DB[Date_Emission])=8)*(YEAR(Fournisseurs_DB[Date_Emission])=TVA_Mensuelle!$B$3)*Fournisseurs_DB[Montant_HT]),0) | D12: =IFERROR(SUMPRODUCT((MONTH(Clients_DB[Date_Emission])=8)*(YEAR(Clients_DB[Date_Emission])=TVA_Mensuelle!$B$3)*Clients_DB[Montant_TVA]),0) | E12: =IFERROR(SUMPRODUCT((MONTH(Fournisseurs_DB[Date_Emission])=8)*(YEAR(Fournisseurs_DB[Date_Emission])=TVA_Mensuelle!$B$3)*Fournisseurs_DB[Montant_TVA]),0) | F12: =D12-E12
A13: Septembre | B13: =IFERROR(SUMPRODUCT((MONTH(Clients_DB[Date_Emission])=9)*(YEAR(Clients_DB[Date_Emission])=TVA_Mensuelle!$B$3)*Clients_DB[Montant_HT]),0) | C13: =IFERROR(SUMPRODUCT((MONTH(Fournisseurs_DB[Date_Emission])=9)*(YEAR(Fournisseurs_DB[Date_Emission])=TVA_Mensuelle!$B$3)*Fournisseurs_DB[Montant_HT]),0) | D13: =IFERROR(SUMPRODUCT((MONTH(Clients_DB[Date_Emission])=9)*(YEAR(Clients_DB[Date_Emission])=TVA_Mensuelle!$B$3)*Clients_DB[Montant_TVA]),0) | E13: =IFERROR(SUMPRODUCT((MONTH(Fournisseurs_DB[Date_Emission])=9)*(YEAR(Fournisseurs_DB[Date_Emission])=TVA_Mensuelle!$B$3)*Fournisseurs_DB[Montant_TVA]),0) | F13: =D13-E13
A14: Octobre | B14: =IFERROR(SUMPRODUCT((MONTH(Clients_DB[Date_Emission])=10)*(YEAR(Clients_DB[Date_Emission])=TVA_Mensuelle!$B$3)*Clients_DB[Montant_HT]),0) | C14: =IFERROR(SUMPRODUCT((MONTH(Fournisseurs_DB[Date_Emission])=10)*(YEAR(Fournisseurs_DB[Date_Emission])=TVA_Mensuelle!$B$3)*Fournisseurs_DB[Montant_HT]),0) | D14: =IFERROR(SUMPRODUCT((MONTH(Clients_DB[Date_Emission])=10)*(YEAR(Clients_DB[Date_Emission])=TVA_Mensuelle!$B$3)*Clients_DB[Montant_TVA]),0) | E14: =IFERROR(SUMPRODUCT((MONTH(Fournisseurs_DB[Date_Emission])=10)*(YEAR(Fournisseurs_DB[Date_Emission])=TVA_Mensuelle!$B$3)*Fournisseurs_DB[Montant_TVA]),0) | F14: =D14-E14
A15: Novembre | B15: =IFERROR(SUMPRODUCT((MONTH(Clients_DB[Date_Emission])=11)*(YEAR(Clients_DB[Date_Emission])=TVA_Mensuelle!$B$3)*Clients_DB[Montant_HT]),0) | C15: =IFERROR(SUMPRODUCT((MONTH(Fournisseurs_DB[Date_Emission])=11)*(YEAR(Fournisseurs_DB[Date_Emission])=TVA_Mensuelle!$B$3)*Fournisseurs_DB[Montant_HT]),0) | D15: =IFERROR(SUMPRODUCT((MONTH(Clients_DB[Date_Emission])=11)*(YEAR(Clients_DB[Date_Emission])=TVA_Mensuelle!$B$3)*Clients_DB[Montant_TVA]),0) | E15: =IFERROR(SUMPRODUCT((MONTH(Fournisseurs_DB[Date_Emission])=11)*(YEAR(Fournisseurs_DB[Date_Emission])=TVA_Mensuelle!$B$3)*Fournisseurs_DB[Montant_TVA]),0) | F15: =D15-E15
A16: Décembre | B16: =IFERROR(SUMPRODUCT((MONTH(Clients_DB[Date_Emission])=12)*(YEAR(Clients_DB[Date_Emission])=TVA_Mensuelle!$B$3)*Clients_DB[Montant_HT]),0) | C16: =IFERROR(SUMPRODUCT((MONTH(Fournisseurs_DB[Date_Emission])=12)*(YEAR(Fournisseurs_DB[Date_Emission])=TVA_Mensuelle!$B$3)*Fournisseurs_DB[Montant_HT]),0) | D16: =IFERROR(SUMPRODUCT((MONTH(Clients_DB[Date_Emission])=12)*(YEAR(Clients_DB[Date_Emission])=TVA_Mensuelle!$B$3)*Clients_DB[Montant_TVA]),0) | E16: =IFERROR(SUMPRODUCT((MONTH(Fournisseurs_DB[Date_Emission])=12)*(YEAR(Fournisseurs_DB[Date_Emission])=TVA_Mensuelle!$B$3)*Fournisseurs_DB[Montant_TVA]),0) | F16: =D16-E16
A17: TOTAL ANNUEL | B17: =SUM(B5:B16) | C17: =SUM(C5:C16) | D17: =SUM(D5:D16) | E17: =SUM(E5:E16) | F17: =SUM(F5:F16)

Sheet TVA_Mensuelle
A1: CALCUL DE TVA MENSUELLE
A3: Année fiscale : | B3: 2026 | C3: ← Saisissez l'année souhaitée
A5: Mois | B5: Année | C5: TVA Collectée (Clients) | D5: TVA Déductible (Fournisseurs) | E5: TVA à Payer (Collectée − Déductible) | F5: Solde Cumulé | G5: Statut | H5: Échéance Déclaration
A6: Janvier | B6: =$B$3 | C6: =IFERROR(SUMPRODUCT((MONTH(Clients_DB[Date_Emission])=1)*(YEAR(Clients_DB[Date_Emission])=$B$3)*Clients_DB[Montant_TVA]),0) | D6: =IFERROR(SUMPRODUCT((MONTH(Fournisseurs_DB[Date_Emission])=1)*(YEAR(Fournisseurs_DB[Date_Emission])=$B$3)*Fournisseurs_DB[Montant_TVA]),0) | E6: =C6-D6 | F6: =E6 | G6: =IF(E6>0,"À PAYER : "&TEXT(E6,"#,##0.00 €"),IF(E6<0,"CRÉDIT : "&TEXT(ABS(E6),"#,##0.00 €"),"Équilibré")) | H6: =DATE($B$3,2,19)
A7: Février | B7: =$B$3 | C7: =IFERROR(SUMPRODUCT((MONTH(Clients_DB[Date_Emission])=2)*(YEAR(Clients_DB[Date_Emission])=$B$3)*Clients_DB[Montant_TVA]),0) | D7: =IFERROR(SUMPRODUCT((MONTH(Fournisseurs_DB[Date_Emission])=2)*(YEAR(Fournisseurs_DB[Date_Emission])=$B$3)*Fournisseurs_DB[Montant_TVA]),0) | E7: =C7-D7 | F7: =F6+E7 | G7: =IF(E7>0,"À PAYER : "&TEXT(E7,"#,##0.00 €"),IF(E7<0,"CRÉDIT : "&TEXT(ABS(E7),"#,##0.00 €"),"Équilibré")) | H7: =DATE($B$3,3,19)
A8: Mars | B8: =$B$3 | C8: =IFERROR(SUMPRODUCT((MONTH(Clients_DB[Date_Emission])=3)*(YEAR(Clients_DB[Date_Emission])=$B$3)*Clients_DB[Montant_TVA]),0) | D8: =IFERROR(SUMPRODUCT((MONTH(Fournisseurs_DB[Date_Emission])=3)*(YEAR(Fournisseurs_DB[Date_Emission])=$B$3)*Fournisseurs_DB[Montant_TVA]),0) | E8: =C8-D8 | F8: =F7+E8 | G8: =IF(E8>0,"À PAYER : "&TEXT(E8,"#,##0.00 €"),IF(E8<0,"CRÉDIT : "&TEXT(ABS(E8),"#,##0.00 €"),"Équilibré")) | H8: =DATE($B$3,4,19)
A9: Avril | B9: =$B$3 | C9: =IFERROR(SUMPRODUCT((MONTH(Clients_DB[Date_Emission])=4)*(YEAR(Clients_DB[Date_Emission])=$B$3)*Clients_DB[Montant_TVA]),0) | D9: =IFERROR(SUMPRODUCT((MONTH(Fournisseurs_DB[Date_Emission])=4)*(YEAR(Fournisseurs_DB[Date_Emission])=$B$3)*Fournisseurs_DB[Montant_TVA]),0) | E9: =C9-D9 | F9: =F8+E9 | G9: =IF(E9>0,"À PAYER : "&TEXT(E9,"#,##0.00 €"),IF(E9<0,"CRÉDIT : "&TEXT(ABS(E9),"#,##0.00 €"),"Équilibré")) | H9: =DATE($B$3,5,19)
A10: Mai | B10: =$B$3 | C10: =IFERROR(SUMPRODUCT((MONTH(Clients_DB[Date_Emission])=5)*(YEAR(Clients_DB[Date_Emission])=$B$3)*Clients_DB[Montant_TVA]),0) | D10: =IFERROR(SUMPRODUCT((MONTH(Fournisseurs_DB[Date_Emission])=5)*(YEAR(Fournisseurs_DB[Date_Emission])=$B$3)*Fournisseurs_DB[Montant_TVA]),0) | E10: =C10-D10 | F10: =F9+E10 | G10: =IF(E10>0,"À PAYER : "&TEXT(E10,"#,##0.00 €"),IF(E10<0,"CRÉDIT : "&TEXT(ABS(E10),"#,##0.00 €"),"Équilibré")) | H10: =DATE($B$3,6,19)
A11: Juin | B11: =$B$3 | C11: =IFERROR(SUMPRODUCT((MONTH(Clients_DB[Date_Emission])=6)*(YEAR(Clients_DB[Date_Emission])=$B$3)*Clients_DB[Montant_TVA]),0) | D11: =IFERROR(SUMPRODUCT((MONTH(Fournisseurs_DB[Date_Emission])=6)*(YEAR(Fournisseurs_DB[Date_Emission])=$B$3)*Fournisseurs_DB[Montant_TVA]),0) | E11: =C11-D11 | F11: =F10+E11 | G11: =IF(E11>0,"À PAYER : "&TEXT(E11,"#,##0.00 €"),IF(E11<0,"CRÉDIT : "&TEXT(ABS(E11),"#,##0.00 €"),"Équilibré")) | H11: =DATE($B$3,7,19)
A12: Juillet | B12: =$B$3 | C12: =IFERROR(SUMPRODUCT((MONTH(Clients_DB[Date_Emission])=7)*(YEAR(Clients_DB[Date_Emission])=$B$3)*Clients_DB[Montant_TVA]),0) | D12: =IFERROR(SUMPRODUCT((MONTH(Fournisseurs_DB[Date_Emission])=7)*(YEAR(Fournisseurs_DB[Date_Emission])=$B$3)*Fournisseurs_DB[Montant_TVA]),0) | E12: =C12-D12 | F12: =F11+E12 | G12: =IF(E12>0,"À PAYER : "&TEXT(E12,"#,##0.00 €"),IF(E12<0,"CRÉDIT : "&TEXT(ABS(E12),"#,##0.00 €"),"Équilibré")) | H12: =DATE($B$3,8,19)
A13: Août | B13: =$B$3 | C13: =IFERROR(SUMPRODUCT((MONTH(Clients_DB[Date_Emission])=8)*(YEAR(Clients_DB[Date_Emission])=$B$3)*Clients_DB[Montant_TVA]),0) | D13: =IFERROR(SUMPRODUCT((MONTH(Fournisseurs_DB[Date_Emission])=8)*(YEAR(Fournisseurs_DB[Date_Emission])=$B$3)*Fournisseurs_DB[Montant_TVA]),0) | E13: =C13-D13 | F13: =F12+E13 | G13: =IF(E13>0,"À PAYER : "&TEXT(E13,"#,##0.00 €"),IF(E13<0,"CRÉDIT : "&TEXT(ABS(E13),"#,##0.00 €"),"Équilibré")) | H13: =DATE($B$3,9,19)
A14: Septembre | B14: =$B$3 | C14: =IFERROR(SUMPRODUCT((MONTH(Clients_DB[Date_Emission])=9)*(YEAR(Clients_DB[Date_Emission])=$B$3)*Clients_DB[Montant_TVA]),0) | D14: =IFERROR(SUMPRODUCT((MONTH(Fournisseurs_DB[Date_Emission])=9)*(YEAR(Fournisseurs_DB[Date_Emission])=$B$3)*Fournisseurs_DB[Montant_TVA]),0) | E14: =C14-D14 | F14: =F13+E14 | G14: =IF(E14>0,"À PAYER : "&TEXT(E14,"#,##0.00 €"),IF(E14<0,"CRÉDIT : "&TEXT(ABS(E14),"#,##0.00 €"),"Équilibré")) | H14: =DATE($B$3,10,19)
A15: Octobre | B15: =$B$3 | C15: =IFERROR(SUMPRODUCT((MONTH(Clients_DB[Date_Emission])=10)*(YEAR(Clients_DB[Date_Emission])=$B$3)*Clients_DB[Montant_TVA]),0) | D15: =IFERROR(SUMPRODUCT((MONTH(Fournisseurs_DB[Date_Emission])=10)*(YEAR(Fournisseurs_DB[Date_Emission])=$B$3)*Fournisseurs_DB[Montant_TVA]),0) | E15: =C15-D15 | F15: =F14+E15 | G15: =IF(E15>0,"À PAYER : "&TEXT(E15,"#,##0.00 €"),IF(E15<0,"CRÉDIT : "&TEXT(ABS(E15),"#,##0.00 €"),"Équilibré")) | H15: =DATE($B$3,11,19)
A16: Novembre | B16: =$B$3 | C16: =IFERROR(SUMPRODUCT((MONTH(Clients_DB[Date_Emission])=11)*(YEAR(Clients_DB[Date_Emission])=$B$3)*Clients_DB[Montant_TVA]),0) | D16: =IFERROR(SUMPRODUCT((MONTH(Fournisseurs_DB[Date_Emission])=11)*(YEAR(Fournisseurs_DB[Date_Emission])=$B$3)*Fournisseurs_DB[Montant_TVA]),0) | E16: =C16-D16 | F16: =F15+E16 | G16: =IF(E16>0,"À PAYER : "&TEXT(E16,"#,##0.00 €"),IF(E16<0,"CRÉDIT : "&TEXT(ABS(E16),"#,##0.00 €"),"Équilibré")) | H16: =DATE($B$3,12,19)
A17: Décembre | B17: =$B$3 | C17: =IFERROR(SUMPRODUCT((MONTH(Clients_DB[Date_Emission])=12)*(YEAR(Clients_DB[Date_Emission])=$B$3)*Clients_DB[Montant_TVA]),0) | D17: =IFERROR(SUMPRODUCT((MONTH(Fournisseurs_DB[Date_Emission])=12)*(YEAR(Fournisseurs_DB[Date_Emission])=$B$3)*Fournisseurs_DB[Montant_TVA]),0) | E17: =C17-D17 | F17: =F16+E17 | G17: =IF(E17>0,"À PAYER : "&TEXT(E17,"#,##0.00 €"),IF(E17<0,"CRÉDIT : "&TEXT(ABS(E17),"#,##0.00 €"),"Équilibré")) | H17: =DATE($B$3+1,1,19)
A18: TOTAL ANNUEL | C18: =SUM(C6:C17) | D18: =SUM(D6:D17) | E18: =SUM(E6:E17) | F18: =F17
A21: SYNTHÈSE PAR TAUX DE TVA
A22: Taux TVA | B22: TVA Collectée (Clients) | C22: TVA Déductible (Fournisseurs) | D22: Solde Net
A23: 0 % | B23: =IFERROR(SUMPRODUCT((Clients_DB[Taux_TVA]=0)*(YEAR(Clients_DB[Date_Emission])=$B$3)*Clients_DB[Montant_TVA]),0) | C23: =IFERROR(SUMPRODUCT((Fournisseurs_DB[Taux_TVA]=0)*(YEAR(Fournisseurs_DB[Date_Emission])=$B$3)*Fournisseurs_DB[Montant_TVA]),0) | D23: =B23-C23
A24: 5,5 % | B24: =IFERROR(SUMPRODUCT((Clients_DB[Taux_TVA]=5.5)*(YEAR(Clients_DB[Date_Emission])=$B$3)*Clients_DB[Montant_TVA]),0) | C24: =IFERROR(SUMPRODUCT((Fournisseurs_DB[Taux_TVA]=5.5)*(YEAR(Fournisseurs_DB[Date_Emission])=$B$3)*Fournisseurs_DB[Montant_TVA]),0) | D24: =B24-C24
A25: 10 % | B25: =IFERROR(SUMPRODUCT((Clients_DB[Taux_TVA]=10)*(YEAR(Clients_DB[Date_Emission])=$B$3)*Clients_DB[Montant_TVA]),0) | C25: =IFERROR(SUMPRODUCT((Fournisseurs_DB[Taux_TVA]=10)*(YEAR(Fournisseurs_DB[Date_Emission])=$B$3)*Fournisseurs_DB[Montant_TVA]),0) | D25: =B25-C25
A26: 20 % | B26: =IFERROR(SUMPRODUCT((Clients_DB[Taux_TVA]=20)*(YEAR(Clients_DB[Date_Emission])=$B$3)*Clients_DB[Montant_TVA]),0) | C26: =IFERROR(SUMPRODUCT((Fournisseurs_DB[Taux_TVA]=20)*(YEAR(Fournisseurs_DB[Date_Emission])=$B$3)*Fournisseurs_DB[Montant_TVA]),0) | D26: =B26-C26

Sheet Guide_Utilisateur
A1: GUIDE UTILISATEUR — SYSTÈME DE GESTION COMPTABLE ECPT
B3: INSTALLATION INITIALE
B4: 1. Exécutez install.bat en tant qu'administrateur.
B5: Ce script installe Python, les bibliothèques et crée le fichier Excel.
B6: 2. Ouvrez EasyCompta.xlsx dans Excel 365.
B7: 3. Enregistrez-le en .xlsm : Fichier → Enregistrer sous → Classeur Excel prenant en charge les macros (*.xlsm).
B8: 4. Ouvrez l'éditeur VBA : Alt + F11.
B9: 5. Importez le module : Fichier → Importer → vba_Comptabilite.bas.
B10: 6. Fermez l'éditeur, puis lancez : Alt + F8 → Setup_Boutons → Exécuter.
B12: IMPORTER UNE FACTURE PDF (AUTOMATIQUE)
B13: 1. Allez sur la feuille PDF_Import.
B14: 2. Cliquez sur « Importer PDF » et sélectionnez votre fichier.
B15: 3. Cliquez sur « Extraire données » — Python analyse le PDF.
... B53: • requirements.txt — dépendances Python.
